Redactix/__init__.py
Redactix/gradio_app.py
Redactix/utils.py
Redactix/data/logo.png
tests/__init__.py
tests/test_utils.py
Redactix-0.1.dist-info/METADATA
Redactix-0.1.dist-info/WHEEL
Redactix-0.1.dist-info/entry_points.txt
Redactix-0.1.dist-info/top_level.txt
Redactix-0.1.dist-info/RECORD
